{"crs": {"type": "name", "properties": {"name": "urn:ogc:def:crs:OGC:1.3:CRS84"}}, "type": "FeatureCollection", "features": [{"geometry": {"type": "Point", "coordinates": [-87.7677, 41.9025]}, "properties": {"TOW_COUNT": 1.0, "YEAR": "2008-01-01 00:00:00-06"}}, {"geometry": {"type": "Point", "coordinates": [-87.7233, 41.8803]}, "properties": {"TOW_COUNT": 1.0, "YEAR": "2008-01-01 00:00:00-06"}}, {"geometry": {"type": "Point", "coordinates": [-87.6678, 41.8914]}, "properties": {"TOW_COUNT": 1.0, "YEAR": "2008-01-01 00:00:00-06"}}, {"geometry": {"type": "Point", "coordinates": [-87.5457, 41.6472]}, "properties": {"TOW_COUNT": 1.0, "YEAR": "2008-01-01 00:00:00-06"}}]}