{"crs": {"type": "name", "properties": {"name": "urn:ogc:def:crs:OGC:1.3:CRS84"}}, "type": "FeatureCollection", "features": [{"geometry": {"type": "Point", "coordinates": [-87.7788, 41.8914]}, "properties": {"TOW_COUNT": 1.0, "YEAR": "2008-01-01 00:00:00-06"}}, {"geometry": {"type": "Point", "coordinates": [-87.7122, 41.8914]}, "properties": {"TOW_COUNT": 1.0, "YEAR": "2008-01-01 00:00:00-06"}}, {"geometry": {"type": "Point", "coordinates": [-87.6789, 41.8914]}, "properties": {"TOW_COUNT": 1.0, "YEAR": "2008-01-01 00:00:00-06"}}, {"geometry": {"type": "Point", "coordinates": [-87.5457, 41.6583]}, "properties": {"TOW_COUNT": 1.0, "YEAR": "2008-01-01 00:00:00-06"}}]}