{"crs": {"type": "name", "properties": {"name": "urn:ogc:def:crs:OGC:1.3:CRS84"}}, "type": "FeatureCollection", "features": [{"geometry": {"type": "Point", "coordinates": [-87.7677, 41.9691]}, "type": "Feature", "properties": {"TOW_COUNT": 1.0, "YEAR": "2001-01-01 00:00:00-06"}}, {"geometry": {"type": "Point", "coordinates": [-87.7344, 41.8803]}, "type": "Feature", "properties": {"TOW_COUNT": 1.0, "YEAR": "2001-01-01 00:00:00-06"}}, {"geometry": {"type": "Point", "coordinates": [-87.6789, 41.9913]}, "type": "Feature", "properties": {"TOW_COUNT": 1.0, "YEAR": "2001-01-01 00:00:00-06"}}, {"geometry": {"type": "Point", "coordinates": [-87.6678, 41.8026]}, "type": "Feature", "properties": {"TOW_COUNT": 1.0, "YEAR": "2001-01-01 00:00:00-06"}}, {"geometry": {"type": "Point", "coordinates": [-87.6567, 41.7693]}, "type": "Feature", "properties": {"TOW_COUNT": 1.0, "YEAR": "2001-01-01 00:00:00-06"}}, {"geometry": {"type": "Point", "coordinates": [-87.6567, 41.8803]}, "type": "Feature", "properties": {"TOW_COUNT": 1.0, "YEAR": "2001-01-01 00:00:00-06"}}, {"geometry": {"type": "Point", "coordinates": [-87.6567, 41.8914]}, "type": "Feature", "properties": {"TOW_COUNT": 1.0, "YEAR": "2001-01-01 00:00:00-06"}}, {"geometry": {"type": "Point", "coordinates": [-87.6345, 41.6916]}, "type": "Feature", "properties": {"TOW_COUNT": 1.0, "YEAR": "2001-01-01 00:00:00-06"}}, {"geometry": {"type": "Point", "coordinates": [-87.6234, 41.7582]}, "type": "Feature", "properties": {"TOW_COUNT": 1.0, "YEAR": "2001-01-01 00:00:00-06"}}]}