{"crs": {"type": "name", "properties": {"name": "urn:ogc:def:crs:OGC:1.3:CRS84"}}, "type": "FeatureCollection", "features": [{"geometry": {"type": "Point", "coordinates": [-87.6456, 41.7582]}, "properties": {"TOW_COUNT": 1.0, "MONTH": "2001-02-01 00:00:00-06"}}]}