{"crs": {"type": "name", "properties": {"name": "urn:ogc:def:crs:OGC:1.3:CRS84"}}, "type": "FeatureCollection", "features": [{"geometry": {"type": "Point", "coordinates": [-87.66225, 41.500125]}, "properties": {"TOW_COUNT": 1.0, "YEAR": "2000-01-01 00:00:00-06"}}, {"geometry": {"type": "Point", "coordinates": [-87.66225, 41.999625]}, "properties": {"TOW_COUNT": 1.0, "YEAR": "2000-01-01 00:00:00-06"}}, {"geometry": {"type": "Point", "coordinates": [-87.620625, 41.87475]}, "properties": {"TOW_COUNT": 1.0, "YEAR": "2000-01-01 00:00:00-06"}}]}