{"crs": {"type": "name", "properties": {"name": "urn:ogc:def:crs:OGC:1.3:CRS84"}}, "type": "FeatureCollection", "features": [{"geometry": {"type": "Point", "coordinates": [-87.7122, 41.8914]}, "properties": {"TOW_COUNT": 1.0, "YEAR": "2007-01-01 00:00:00-06"}}, {"geometry": {"type": "Point", "coordinates": [-87.6123, 41.7249]}, "properties": {"TOW_COUNT": 1.0, "YEAR": "2007-01-01 00:00:00-06"}}]}