{"crs": {"type": "name", "properties": {"name": "urn:ogc:def:crs:OGC:1.3:CRS84"}}, "type": "FeatureCollection", "features": [{"geometry": {"type": "Point", "coordinates": [-87.7011, 41.9247]}, "properties": {"TOW_COUNT": 1.0, "MONTH": "2003-01-01 00:00:00-06"}}]}