{"crs": {"type": "name", "properties": {"name": "urn:ogc:def:crs:OGC:1.3:CRS84"}}, "type": "FeatureCollection", "features": [{"geometry": {"type": "Point", "coordinates": [-87.7788, 41.958]}, "properties": {"TOW_COUNT": 1.0, "YEAR": "2001-01-01 00:00:00-06"}}, {"geometry": {"type": "Point", "coordinates": [-87.7455, 41.8914]}, "properties": {"TOW_COUNT": 1.0, "YEAR": "2001-01-01 00:00:00-06"}}, {"geometry": {"type": "Point", "coordinates": [-87.6789, 41.7915]}, "properties": {"TOW_COUNT": 1.0, "YEAR": "2001-01-01 00:00:00-06"}}, {"geometry": {"type": "Point", "coordinates": [-87.6789, 41.9913]}, "properties": {"TOW_COUNT": 1.0, "YEAR": "2001-01-01 00:00:00-06"}}, {"geometry": {"type": "Point", "coordinates": [-87.6456, 41.6916]}, "properties": {"TOW_COUNT": 1.0, "YEAR": "2001-01-01 00:00:00-06"}}, {"geometry": {"type": "Point", "coordinates": [-87.6456, 41.7582]}, "properties": {"TOW_COUNT": 1.0, "YEAR": "2001-01-01 00:00:00-06"}}, {"geometry": {"type": "Point", "coordinates": [-87.6456, 41.8914]}, "properties": {"TOW_COUNT": 2.0, "YEAR": "2001-01-01 00:00:00-06"}}, {"geometry": {"type": "Point", "coordinates": [-87.6123, 41.7582]}, "properties": {"TOW_COUNT": 1.0, "YEAR": "2001-01-01 00:00:00-06"}}]}